LICENSE
MANIFEST.in
README.rst
setup.py
django_pay2pay.egg-info/PKG-INFO
django_pay2pay.egg-info/SOURCES.txt
django_pay2pay.egg-info/dependency_links.txt
django_pay2pay.egg-info/requires.txt
django_pay2pay.egg-info/top_level.txt
pay2pay/__init__.py
pay2pay/__init__.pyc
pay2pay/admin.py
pay2pay/admin.pyc
pay2pay/conf.py
pay2pay/conf.pyc
pay2pay/factories.py
pay2pay/factories.pyc
pay2pay/forms.py
pay2pay/forms.pyc
pay2pay/models.py
pay2pay/models.pyc
pay2pay/signals.py
pay2pay/signals.pyc
pay2pay/tests.py
pay2pay/tests.pyc
pay2pay/urls.py
pay2pay/urls.pyc
pay2pay/utils.py
pay2pay/utils.pyc
pay2pay/views.py
pay2pay/views.pyc
pay2pay/migrations/0001_initial.py
pay2pay/migrations/0001_initial.pyc
pay2pay/migrations/__init__.py
pay2pay/migrations/__init__.pyc
pay2pay/templates/pay2pay/pay_page.html
pay2pay/templates/pay2pay/payment_fail.html
pay2pay/templates/pay2pay/payment_success.html